dorkscan/__init__.py
dorkscan/__main__.py
dorkscan/engines.py
dorkscan/network.py
dorkscan/types.py
dorkscan-0.1.post1.dist-info/LICENSE
dorkscan-0.1.post1.dist-info/METADATA
dorkscan-0.1.post1.dist-info/WHEEL
dorkscan-0.1.post1.dist-info/top_level.txt
dorkscan-0.1.post1.dist-info/RECORD
