Metadata-Version: 2.1
Name: dorkscan
Version: 0.1.post1
Summary: An atypical search engine parser
Home-page: http://gitlab.com/unkwn1/dorkscan
Author: unkwn1
Author-email: unkwn1@tutanota.com
License: MIT
Project-URL: Issues, https://gitlab.com/unkwn1/dorkscan/-/issues
Project-URL: Source, https://gitlab.com/unkwn1/dorkscan/-/tree/main
Project-URL: DorkScanner, https://github.com/balgogan/dorkscanner
Project-URL: GitHub, https://github.com/jessefogarty/
Keywords: dorking,google dork,web parser,web scraping
Platform: UNKNOWN
Classifier: Development Status :: 3 - Alpha
Classifier: Programming Language :: Python :: 3.10
Classifier: Topic :: Software Development :: Libraries :: Python Modules
License-File: LICENSE
Requires-Dist: beautifulsoup4 (>=4.10.0)
Requires-Dist: bs4 (>=0.0.1)
Requires-Dist: certifi (>=2021.10.8)
Requires-Dist: charset-normalizer (>=2.0.9)
Requires-Dist: colorama (>=0.4.4)
Requires-Dist: commonmark (>=0.9.1)
Requires-Dist: idna (>=3.3)
Requires-Dist: Pygments (>=2.10.0)
Requires-Dist: requests (>=2.26.0)
Requires-Dist: rich (>=10.16.1)
Requires-Dist: soupsieve (>=2.3.1)
Requires-Dist: urllib3 (>=1.26.7)
